{
  "questions": [
    {
      "num": "1",
      "question": "Как называется продольная вертикальная плоскость, делящая судно на две симметричные части: левую и правую?",
      "answers": [
        {
          "id": 1,
          "answer": "Мидель-шпангоута"
        },
        {
          "id": 2,
          "answer": "Фронтальная"
        },
        {
          "id": 3,
          "answer": "Основная"
        },
        {
          "id": 4,
          "answer": "Диаметральная"
        }
      ],
      "true_answer": 4
    },
    {
      "num": "2",
      "question": "Как соответственно называются приспособления на спасательном жилете, обозначенные цифрами 1, 2 и 3?",
      "answers": [
        {
          "id": 1,
          "answer": "Ремни крепления, свисток и лампочка"
        },
        {
          "id": 2,
          "answer": "Ремни для транспортировки, батарейка и свисток"
        },
        {
          "id": 3,
          "answer": "Ремни крепления, свисток и батарейка"
        },
        {
          "id": 4,
          "answer": "Упаковочный ремень, лампочка и батарейка"
        }
      ],
      "true_answer": 3
    },
    {
      "num": "3",
      "question": "Какое действие считается наиболее эффективным для предупреждения чрезмерного сближения, при наличии достаточного водного пространства?",
      "answers": [
        {
          "id": 1,
          "answer": "Существенное изменение курса"
        },
        {
          "id": 2,
          "answer": "Постепенное изменение курса"
        },
        {
          "id": 3,
          "answer": "Существенное изменение скорости"
        },
        {
          "id": 4,
          "answer": "Постепенное изменение скорости"
        }
      ],
      "true_answer": 1
    },
    {
      "num": "4",
      "question": "Какова основная опасность, возникающая при приближении к идущему судну большого размера?",
      "answers": [
        {
          "id": 1,
          "answer": "Влияние волн, возникающих при движении большого судна"
        },
        {
          "id": 2,
          "answer": "Влияние эффекта присасывания"
        },
        {
          "id": 3,
          "answer": "Падение с большого судна грузов или тяжелых предметов"
        },
        {
          "id": 4,
          "answer": "Применение экипажем большого судна антипиратских и антитеррористических мер"
        }
      ],
      "true_answer": 2
    },
    {
      "num": "5",
      "question": "Для чего могут применяться толчки на верхнюю часть живота пострадавшего?",
      "answers": [
        {
          "id": 1,
          "answer": "Для искусственной вентиляции легких."
        },
        {
          "id": 2,
          "answer": "Для удаления инородного тела из пищевода."
        },
        {
          "id": 3,
          "answer": "Для уменьшения болевого синдрома при переломе ребер."
        },
        {
          "id": 4,
          "answer": "Для удаления инородного тела из верхних дыхательных путей."
        }
      ],
      "true_answer": 4
    },
    {
      "num": "6",
      "question": "Какой из перечисленных признаков является основным признаком перелома костей?",
      "answers": [
        {
          "id": 1,
          "answer": "Ограничение подвижности"
        },
        {
          "id": 2,
          "answer": "Бледность тканей"
        },
        {
          "id": 3,
          "answer": "Отечность тканей"
        },
        {
          "id": 4,
          "answer": "Нехарактерный изгиб кости"
        }
      ],
      "true_answer": 4
    },
    {
      "num": "7",
      "question": "Какие действия должен предпринять судоводитель при выводе маломерного судна из большой суводи?",
      "answers": [
        {
          "id": 1,
          "answer": "Увеличить ход и пройти через центр суводи"
        },
        {
          "id": 2,
          "answer": "Вести судно по внешнему краю суводи и, увеличивая ход, выходить к стрежню"
        },
        {
          "id": 3,
          "answer": "Вести судно по внешнему краю суводи и, уменьшая ход, выходить к стрежню"
        },
        {
          "id": 4,
          "answer": "Уменьшить ход и резко выходить к стрежню"
        }
      ],
      "true_answer": 2
    },
    {
      "num": "8",
      "question": "Как называется способность судна удерживать заданное направление движения при неизменном положении руля и изменять на ходу направление своего движения под действием руля?",
      "answers": [
        {
          "id": 1,
          "answer": "Поворотливость"
        },
        {
          "id": 2,
          "answer": "Ходкость"
        },
        {
          "id": 3,
          "answer": "Управляемость"
        },
        {
          "id": 4,
          "answer": "Устойчивость на курсе"
        }
      ],
      "true_answer": 3
    },
    {
      "num": "9",
      "question": "Какое действие судоводителя не допустимо во время посадки пассажиров, при их нахождении в воде?",
      "answers": [
        {
          "id": 1,
          "answer": "Нажатие на рычаг акселератора;"
        },
        {
          "id": 2,
          "answer": "Выключение двигателя;"
        },
        {
          "id": 3,
          "answer": "Включение двигателя;"
        },
        {
          "id": 4,
          "answer": "Отключение шнура безопасности от аварийного выключателя двигателя."
        }
      ],
      "true_answer": 2
    },
    {
      "num": "10",
      "question": "Что необходимо предпринять в случае обнаружении подтёков топлива во время осмотра двигателя в эксплуатации?",
      "answers": [
        {
          "id": 1,
          "answer": "принять меры для немедленного устранения неисправности;"
        },
        {
          "id": 2,
          "answer": "долить масло в двигатель, чтобы избежать его поломки;"
        },
        {
          "id": 3,
          "answer": "подать заявку на ремонт двигателя;"
        },
        {
          "id": 4,
          "answer": "продолжить движение."
        }
      ],
      "true_answer": 1
    }
  ]
}
